{
    "id": "org.kde.artikulate",
    "runtime": "org.kde.Platform",
    "runtime-version": "5.15-24.08",
    "sdk": "org.kde.Sdk",
    "command": "artikulate",
    "rename-icon": "artikulate",
    "finish-args": [
        "--share=network",
        "--share=ipc",
        "--socket=fallback-x11",
        "--socket=wayland",
        "--socket=pulseaudio",
        "--device=dri"
    ],
    "modules": [
        {
            "name": "artikulate",
            "buildsystem": "cmake-ninja",
            "sources": [
                {
                    "type": "archive",
                    "url": "https://download.kde.org/stable/release-service/25.04.0/src/artikulate-25.04.0.tar.xz",
                    "sha256": "06579caedb2f517166d6fe87ea8b0f97c1f6e99289aaf9c5dfea01c386487668",
                    "x-checker-data": {
                        "type": "anitya",
                        "project-id": 8763,
                        "stable-only": true,
                        "url-template": "https://download.kde.org/stable/release-service/$version/src/artikulate-$version.tar.xz"
                    }
                }
            ]
        }
    ]
}
